pycstruct/__init__.py
pycstruct/cparser.py
pycstruct/instance.py
pycstruct/pycstruct.py
pycstruct-0.12.2.dist-info/LICENSE.txt
pycstruct-0.12.2.dist-info/METADATA
pycstruct-0.12.2.dist-info/WHEEL
pycstruct-0.12.2.dist-info/top_level.txt
pycstruct-0.12.2.dist-info/RECORD
