Metadata-Version: 2.1
Name: pycstruct
Version: 0.12.2
Summary: Binary data handling in Python using dictionaries
Home-page: http://github.com/midstar/pycstruct
Author: Joel Midstjärna
Author-email: joel.midstjarna@gmail.com
License: MIT
Project-URL: Bug Tracker, https://github.com/midstar/pycstruct/issues
Project-URL: Documentation, https://pycstruct.readthedocs.io/en/latest/
Project-URL: Source Code, https://github.com/midstar/pycstruct
Keywords: struct,enum,bitfield,binary,protocol,dict,dictionary
Classifier: Development Status :: 3 - Alpha
Classifier: Intended Audience :: Developers
Classifier: Topic :: Software Development :: Build Tools
Classifier: License :: OSI Approved :: MIT License
Classifier: Programming Language :: Python :: 3
Classifier: Programming Language :: Python :: 3.4
Classifier: Programming Language :: Python :: 3.5
Classifier: Programming Language :: Python :: 3.6
Classifier: Programming Language :: Python :: 3.7
Classifier: Programming Language :: Python :: 3.8
Classifier: Programming Language :: Python :: 3.9
Classifier: Programming Language :: Python :: 3.10
Classifier: Programming Language :: Python :: 3.11
License-File: LICENSE.txt
